AUTHORS
CHANGES.md
LICENSE
MANIFEST.in
Makefile
README.md
TODO.txt
requirements.txt
setup.py
bin/mantash
manta/__init__.py
manta/appdirs.py
manta/auth.py
manta/client.py
manta/cmdln.py
manta/errors.py
manta/version.py
manta.egg-info/PKG-INFO
manta.egg-info/SOURCES.txt
manta.egg-info/dependency_links.txt
manta.egg-info/not-zip-safe
manta.egg-info/requires.txt
manta.egg-info/top_level.txt
test/common.py
test/test.py
test/test_auth.py
test/test_mantaclient.py
test/test_mantash.py
test/testall.py
test/testlib.py