Metadata-Version: 1.1
Name: manta
Version: 2.7.0
Summary: A Python SDK for Joyent's Manta service
Home-page: https://github.com/joyent/python-manta
Author: Joyent
Author-email: support@joyent.com
License: MIT
Platform: any
Classifier: Development Status :: 4 - Beta
Classifier: Intended Audience :: Developers
Classifier: License :: OSI Approved :: MIT License
Classifier: Programming Language :: Python
Classifier: Programming Language :: Python :: 2
Classifier: Programming Language :: Python :: 2.6
Classifier: Programming Language :: Python :: 2.7
Classifier: Operating System :: OS Independent
Classifier: Topic :: Software Development :: Libraries :: Python Modules
